qtasks_webview/__init__.py
qtasks_webview/version.py
qtasks_webview-0.0.1.dist-info/METADATA
qtasks_webview-0.0.1.dist-info/WHEEL
qtasks_webview-0.0.1.dist-info/top_level.txt
qtasks_webview-0.0.1.dist-info/RECORD
