Metadata-Version: 2.4
Name: qtasks_webview
Version: 0.0.1
Summary: Web Framework for QTasks
Author-email: txello <txello@inbox.ru>
Project-URL: Homepage, https://github.com/txello/qtasks_webview
Project-URL: Issues, https://github.com/txello/qtasks_webview/issues
Classifier: Programming Language :: Python :: 3
Classifier: License :: OSI Approved :: MIT License
Classifier: Operating System :: OS Independent
Requires-Python: >=3.8
